{
    "/js/app.js": "/js/app.js",
    "/css/app.css": "/css/app.css",
    "/js/app.70910cbb5649004cfd3d.hot-update.js": "/js/app.70910cbb5649004cfd3d.hot-update.js",
    "/js/app.f7cdfee03165d255e1f5.hot-update.js": "/js/app.f7cdfee03165d255e1f5.hot-update.js",
    "/js/app.b2132ab18d25ca1a7673.hot-update.js": "/js/app.b2132ab18d25ca1a7673.hot-update.js",
    "/js/app.b69ebec6bed665a2609a.hot-update.js": "/js/app.b69ebec6bed665a2609a.hot-update.js",
    "/js/app.5f82bd1b970f92c6713c.hot-update.js": "/js/app.5f82bd1b970f92c6713c.hot-update.js",
    "/js/app.5d61888c3d055c6c71a2.hot-update.js": "/js/app.5d61888c3d055c6c71a2.hot-update.js",
    "/js/app.58767eed3dfb2c4ce886.hot-update.js": "/js/app.58767eed3dfb2c4ce886.hot-update.js",
    "/js/app.fecd8fa5b5e9d3309053.hot-update.js": "/js/app.fecd8fa5b5e9d3309053.hot-update.js",
    "/js/app.137f253a19c53c60ee02.hot-update.js": "/js/app.137f253a19c53c60ee02.hot-update.js",
    "/js/app.32c821fe5df77b953d3b.hot-update.js": "/js/app.32c821fe5df77b953d3b.hot-update.js",
    "/js/app.1ff3702e7e9d878ccc7d.hot-update.js": "/js/app.1ff3702e7e9d878ccc7d.hot-update.js",
    "/js/app.32c62e0f8076731b7eef.hot-update.js": "/js/app.32c62e0f8076731b7eef.hot-update.js",
    "/js/app.2636f83ef4862940bae7.hot-update.js": "/js/app.2636f83ef4862940bae7.hot-update.js",
    "/js/app.bb773197ad3543ea02c2.hot-update.js": "/js/app.bb773197ad3543ea02c2.hot-update.js",
    "/js/app.92f3f2a86d2a9efcfdc6.hot-update.js": "/js/app.92f3f2a86d2a9efcfdc6.hot-update.js",
    "/js/app.143ca256546e0c5912c6.hot-update.js": "/js/app.143ca256546e0c5912c6.hot-update.js",
    "/js/app.c29b18a8425b0d91f7f0.hot-update.js": "/js/app.c29b18a8425b0d91f7f0.hot-update.js",
    "/js/app.f654ade636dec1cddd7e.hot-update.js": "/js/app.f654ade636dec1cddd7e.hot-update.js",
    "/js/app.255c3bc090b0984e7905.hot-update.js": "/js/app.255c3bc090b0984e7905.hot-update.js",
    "/js/app.2b24648048dcd98111b8.hot-update.js": "/js/app.2b24648048dcd98111b8.hot-update.js",
    "/js/app.daeb3544e24763eff33b.hot-update.js": "/js/app.daeb3544e24763eff33b.hot-update.js",
    "/js/app.ff5263843bef0ae0c05f.hot-update.js": "/js/app.ff5263843bef0ae0c05f.hot-update.js",
    "/js/app.46387ce7b8e5e679f517.hot-update.js": "/js/app.46387ce7b8e5e679f517.hot-update.js",
    "/js/app.439e4533763501cafd65.hot-update.js": "/js/app.439e4533763501cafd65.hot-update.js",
    "/js/app.bab6171b476c5744bd58.hot-update.js": "/js/app.bab6171b476c5744bd58.hot-update.js",
    "/js/app.71b8229170e965654c1f.hot-update.js": "/js/app.71b8229170e965654c1f.hot-update.js",
    "/js/app.51d76a33a06443b83860.hot-update.js": "/js/app.51d76a33a06443b83860.hot-update.js",
    "/js/app.d5eba92de3a538a8f984.hot-update.js": "/js/app.d5eba92de3a538a8f984.hot-update.js",
    "/js/app.2ddaa0bd5619231cc657.hot-update.js": "/js/app.2ddaa0bd5619231cc657.hot-update.js",
    "/js/app.f5b6714b6df41724034b.hot-update.js": "/js/app.f5b6714b6df41724034b.hot-update.js",
    "/js/app.bbf06a3e181bb3f64ec6.hot-update.js": "/js/app.bbf06a3e181bb3f64ec6.hot-update.js",
    "/js/app.4ee830687d6b3a4a0a00.hot-update.js": "/js/app.4ee830687d6b3a4a0a00.hot-update.js",
    "/js/app.73150422d0e7b209c10d.hot-update.js": "/js/app.73150422d0e7b209c10d.hot-update.js",
    "/js/app.15d6d45895be34861a90.hot-update.js": "/js/app.15d6d45895be34861a90.hot-update.js",
    "/js/app.e2a5be3060b3213535c2.hot-update.js": "/js/app.e2a5be3060b3213535c2.hot-update.js",
    "/js/app.ee67cab5a680f2cb7d4e.hot-update.js": "/js/app.ee67cab5a680f2cb7d4e.hot-update.js",
    "/js/app.9b5ae9be5d5eca3a4f35.hot-update.js": "/js/app.9b5ae9be5d5eca3a4f35.hot-update.js",
    "/js/app.f2436258071376e6e27f.hot-update.js": "/js/app.f2436258071376e6e27f.hot-update.js",
    "/js/app.217a628d10b8d69e41c5.hot-update.js": "/js/app.217a628d10b8d69e41c5.hot-update.js",
    "/js/app.acb65f3a86005914069e.hot-update.js": "/js/app.acb65f3a86005914069e.hot-update.js",
    "/js/app.af7abe9108a99b74316e.hot-update.js": "/js/app.af7abe9108a99b74316e.hot-update.js",
    "/js/app.c370a2e6912780984cfb.hot-update.js": "/js/app.c370a2e6912780984cfb.hot-update.js",
    "/js/app.e8b79c590e83787d2a74.hot-update.js": "/js/app.e8b79c590e83787d2a74.hot-update.js",
    "/js/app.482c8e61918eea467f4f.hot-update.js": "/js/app.482c8e61918eea467f4f.hot-update.js",
    "/js/app.5764b6cb5667ceb7f7ea.hot-update.js": "/js/app.5764b6cb5667ceb7f7ea.hot-update.js",
    "/js/app.ccfddae4bb10dc008c4d.hot-update.js": "/js/app.ccfddae4bb10dc008c4d.hot-update.js",
    "/js/app.8a9860c72abfe7853cdf.hot-update.js": "/js/app.8a9860c72abfe7853cdf.hot-update.js",
    "/js/app.2efc494282e442c2d555.hot-update.js": "/js/app.2efc494282e442c2d555.hot-update.js",
    "/js/app.1421c8bd9eefc2feef1b.hot-update.js": "/js/app.1421c8bd9eefc2feef1b.hot-update.js",
    "/js/app.17ddd60dfef8930e8ddb.hot-update.js": "/js/app.17ddd60dfef8930e8ddb.hot-update.js",
    "/js/app.de42b0e2a9860f2247b5.hot-update.js": "/js/app.de42b0e2a9860f2247b5.hot-update.js",
    "/js/app.a6c21ba8c06bafdf168b.hot-update.js": "/js/app.a6c21ba8c06bafdf168b.hot-update.js",
    "/js/app.1793f3aba1f19fc4bdbe.hot-update.js": "/js/app.1793f3aba1f19fc4bdbe.hot-update.js",
    "/js/app.81a4e0c9c1aebd8e814e.hot-update.js": "/js/app.81a4e0c9c1aebd8e814e.hot-update.js",
    "/js/app.73a71f4880acc911c209.hot-update.js": "/js/app.73a71f4880acc911c209.hot-update.js",
    "/js/app.8a5d6bd03ed7a6fcad02.hot-update.js": "/js/app.8a5d6bd03ed7a6fcad02.hot-update.js",
    "/js/app.7107996afe10f0ea5614.hot-update.js": "/js/app.7107996afe10f0ea5614.hot-update.js",
    "/js/app.78167d0a0cc4edcba796.hot-update.js": "/js/app.78167d0a0cc4edcba796.hot-update.js",
    "/js/app.8ded60b85fe8938fb56d.hot-update.js": "/js/app.8ded60b85fe8938fb56d.hot-update.js",
    "/js/app.a9b49488b0565b762f6a.hot-update.js": "/js/app.a9b49488b0565b762f6a.hot-update.js",
    "/js/app.17467cd485460cd33368.hot-update.js": "/js/app.17467cd485460cd33368.hot-update.js",
    "/js/app.b5075c84ad01b6833962.hot-update.js": "/js/app.b5075c84ad01b6833962.hot-update.js",
    "/js/app.3a02ff42df98ad8314d1.hot-update.js": "/js/app.3a02ff42df98ad8314d1.hot-update.js",
    "/js/app.9a2c889a9e7b4333c13e.hot-update.js": "/js/app.9a2c889a9e7b4333c13e.hot-update.js",
    "/js/app.1c383ffce0fa401dc4e7.hot-update.js": "/js/app.1c383ffce0fa401dc4e7.hot-update.js",
    "/js/app.cc4e44fe2cab481445c9.hot-update.js": "/js/app.cc4e44fe2cab481445c9.hot-update.js",
    "/js/app.05cf0fda96321ca5baf3.hot-update.js": "/js/app.05cf0fda96321ca5baf3.hot-update.js",
    "/js/app.873b5656c935019dde29.hot-update.js": "/js/app.873b5656c935019dde29.hot-update.js",
    "/js/app.9ecab4adb04a3e3eff73.hot-update.js": "/js/app.9ecab4adb04a3e3eff73.hot-update.js",
    "/js/app.e9d61f71f7259b8c5346.hot-update.js": "/js/app.e9d61f71f7259b8c5346.hot-update.js",
    "/js/app.46baeef4ec9b973b56b9.hot-update.js": "/js/app.46baeef4ec9b973b56b9.hot-update.js",
    "/js/app.c361dc2ffc842512a290.hot-update.js": "/js/app.c361dc2ffc842512a290.hot-update.js",
    "/js/app.289489456b16d21e87fd.hot-update.js": "/js/app.289489456b16d21e87fd.hot-update.js",
    "/js/app.27f7432060a36bea8a63.hot-update.js": "/js/app.27f7432060a36bea8a63.hot-update.js",
    "/js/app.bca99ee69a371d004afc.hot-update.js": "/js/app.bca99ee69a371d004afc.hot-update.js",
    "/js/app.83420ddbb35dbaad3239.hot-update.js": "/js/app.83420ddbb35dbaad3239.hot-update.js",
    "/js/app.e9699776a2ec198ae4b2.hot-update.js": "/js/app.e9699776a2ec198ae4b2.hot-update.js",
    "/js/app.0e436e420654d7dbed0d.hot-update.js": "/js/app.0e436e420654d7dbed0d.hot-update.js",
    "/js/app.cdb04d31397f5507d9c9.hot-update.js": "/js/app.cdb04d31397f5507d9c9.hot-update.js",
    "/js/app.095395802903af8cb97a.hot-update.js": "/js/app.095395802903af8cb97a.hot-update.js",
    "/js/app.866f5438ecd910c8fb01.hot-update.js": "/js/app.866f5438ecd910c8fb01.hot-update.js",
    "/js/app.f6f4e5ad01a79a770e2a.hot-update.js": "/js/app.f6f4e5ad01a79a770e2a.hot-update.js",
    "/js/app.8b9c64e1e230d6fa8426.hot-update.js": "/js/app.8b9c64e1e230d6fa8426.hot-update.js",
    "/js/app.994b4c726bfc28bcde6c.hot-update.js": "/js/app.994b4c726bfc28bcde6c.hot-update.js",
    "/js/app.7b03dcb2ab176389ea56.hot-update.js": "/js/app.7b03dcb2ab176389ea56.hot-update.js",
    "/js/app.cffbfd26a132975c63e3.hot-update.js": "/js/app.cffbfd26a132975c63e3.hot-update.js",
    "/js/app.283af875c526f8eeb3da.hot-update.js": "/js/app.283af875c526f8eeb3da.hot-update.js",
    "/js/app.92318ffbdbb70697b851.hot-update.js": "/js/app.92318ffbdbb70697b851.hot-update.js",
    "/js/app.a46705999af6d2791f1b.hot-update.js": "/js/app.a46705999af6d2791f1b.hot-update.js",
    "/js/app.14264feb107ad1b6398e.hot-update.js": "/js/app.14264feb107ad1b6398e.hot-update.js",
    "/js/app.b9b2cf09fc6a5e41e6a4.hot-update.js": "/js/app.b9b2cf09fc6a5e41e6a4.hot-update.js",
    "/js/app.76432465e09e226d0693.hot-update.js": "/js/app.76432465e09e226d0693.hot-update.js",
    "/js/app.26ea395beb41f27a55bd.hot-update.js": "/js/app.26ea395beb41f27a55bd.hot-update.js",
    "/js/app.244312e6bbbabceb1e94.hot-update.js": "/js/app.244312e6bbbabceb1e94.hot-update.js",
    "/js/app.3efdd6ac634f3c4076b3.hot-update.js": "/js/app.3efdd6ac634f3c4076b3.hot-update.js",
    "/js/app.6d9679e1bdd1651ad707.hot-update.js": "/js/app.6d9679e1bdd1651ad707.hot-update.js",
    "/js/app.b21033475fbb951cfba1.hot-update.js": "/js/app.b21033475fbb951cfba1.hot-update.js",
    "/js/app.5cb9abeaa180ee287c04.hot-update.js": "/js/app.5cb9abeaa180ee287c04.hot-update.js",
    "/js/app.53f34fd9d07c392aa898.hot-update.js": "/js/app.53f34fd9d07c392aa898.hot-update.js",
    "/js/app.d1ab5f31ab1f38a08065.hot-update.js": "/js/app.d1ab5f31ab1f38a08065.hot-update.js",
    "/js/app.1bd6a4548129e8be9122.hot-update.js": "/js/app.1bd6a4548129e8be9122.hot-update.js",
    "/js/app.5fea46d82a39dc0f6f2f.hot-update.js": "/js/app.5fea46d82a39dc0f6f2f.hot-update.js",
    "/js/app.ffaf9cf2aea13aea92f4.hot-update.js": "/js/app.ffaf9cf2aea13aea92f4.hot-update.js",
    "/js/app.9c7aa7377ab3fabd7d02.hot-update.js": "/js/app.9c7aa7377ab3fabd7d02.hot-update.js",
    "/js/app.f6901adbc6bed693031d.hot-update.js": "/js/app.f6901adbc6bed693031d.hot-update.js",
    "/js/app.662823bc210b7b3b56d0.hot-update.js": "/js/app.662823bc210b7b3b56d0.hot-update.js",
    "/js/app.b585695ec234c8f434af.hot-update.js": "/js/app.b585695ec234c8f434af.hot-update.js",
    "/js/app.2748b23d1b96543329e6.hot-update.js": "/js/app.2748b23d1b96543329e6.hot-update.js",
    "/js/app.3a36a5f37942e5789981.hot-update.js": "/js/app.3a36a5f37942e5789981.hot-update.js",
    "/js/app.788073960ecd87917516.hot-update.js": "/js/app.788073960ecd87917516.hot-update.js",
    "/js/app.a52825c6f9951dbdfa74.hot-update.js": "/js/app.a52825c6f9951dbdfa74.hot-update.js",
    "/js/app.77ea4a8f1fce737018f5.hot-update.js": "/js/app.77ea4a8f1fce737018f5.hot-update.js",
    "/js/app.0a99b40abf9677a998b7.hot-update.js": "/js/app.0a99b40abf9677a998b7.hot-update.js",
    "/js/app.09e26b4e89649345ba54.hot-update.js": "/js/app.09e26b4e89649345ba54.hot-update.js",
    "/js/app.9a48ff608c6a6b37cc28.hot-update.js": "/js/app.9a48ff608c6a6b37cc28.hot-update.js",
    "/js/app.4b2b1de0bf6989806397.hot-update.js": "/js/app.4b2b1de0bf6989806397.hot-update.js",
    "/js/app.576675d5ba81f7f1c8b3.hot-update.js": "/js/app.576675d5ba81f7f1c8b3.hot-update.js",
    "/js/app.a6a689c68852af54f5b0.hot-update.js": "/js/app.a6a689c68852af54f5b0.hot-update.js",
    "/js/app.bf31041b938d83838bab.hot-update.js": "/js/app.bf31041b938d83838bab.hot-update.js",
    "/js/app.9854aa36f5365e679581.hot-update.js": "/js/app.9854aa36f5365e679581.hot-update.js",
    "/js/app.6eb719d0b4e408c6da7d.hot-update.js": "/js/app.6eb719d0b4e408c6da7d.hot-update.js",
    "/js/app.b32c823f8db46907f1c4.hot-update.js": "/js/app.b32c823f8db46907f1c4.hot-update.js",
    "/js/app.65e9efe4bf0356c21c0e.hot-update.js": "/js/app.65e9efe4bf0356c21c0e.hot-update.js",
    "/js/app.b6dbe7a84d99a3f26c12.hot-update.js": "/js/app.b6dbe7a84d99a3f26c12.hot-update.js",
    "/js/app.d74d8dd5f6e383246e1e.hot-update.js": "/js/app.d74d8dd5f6e383246e1e.hot-update.js",
    "/js/app.437016e313a228c00947.hot-update.js": "/js/app.437016e313a228c00947.hot-update.js",
    "/js/app.ddcfdede75ce46826585.hot-update.js": "/js/app.ddcfdede75ce46826585.hot-update.js",
    "/js/app.936f33e03b69c81a6a21.hot-update.js": "/js/app.936f33e03b69c81a6a21.hot-update.js",
    "/js/app.f85c0fa69618c1bf6497.hot-update.js": "/js/app.f85c0fa69618c1bf6497.hot-update.js",
    "/js/app.d706cca839305dcafb08.hot-update.js": "/js/app.d706cca839305dcafb08.hot-update.js",
    "/js/app.237b0120c80cc64d250f.hot-update.js": "/js/app.237b0120c80cc64d250f.hot-update.js",
    "/js/app.5c053ba6a8bf015d4a1e.hot-update.js": "/js/app.5c053ba6a8bf015d4a1e.hot-update.js",
    "/js/app.87dbd696e02285187f77.hot-update.js": "/js/app.87dbd696e02285187f77.hot-update.js",
    "/js/app.3d44aa98e4c9da8dc748.hot-update.js": "/js/app.3d44aa98e4c9da8dc748.hot-update.js",
    "/js/app.eee047ba016903a3335c.hot-update.js": "/js/app.eee047ba016903a3335c.hot-update.js",
    "/js/app.e48c021d8940c57e4515.hot-update.js": "/js/app.e48c021d8940c57e4515.hot-update.js",
    "/js/app.d99eb18d97a61face9de.hot-update.js": "/js/app.d99eb18d97a61face9de.hot-update.js",
    "/js/app.1f4657ebc351d87cd8a8.hot-update.js": "/js/app.1f4657ebc351d87cd8a8.hot-update.js",
    "/js/app.803289b9470ff6149329.hot-update.js": "/js/app.803289b9470ff6149329.hot-update.js",
    "/js/app.d40e19c0544434b6e039.hot-update.js": "/js/app.d40e19c0544434b6e039.hot-update.js",
    "/js/app.9d8e44430e60032feeee.hot-update.js": "/js/app.9d8e44430e60032feeee.hot-update.js",
    "/js/app.bb45a2d86f937b0dcadf.hot-update.js": "/js/app.bb45a2d86f937b0dcadf.hot-update.js",
    "/js/app.29fd4068a1ace5f7cc0d.hot-update.js": "/js/app.29fd4068a1ace5f7cc0d.hot-update.js"
}
